{"ResponseCode":200,"ResponseMessage":"SUCCESS: Jobs returned: 1","JobList":[{"JobNumber":"304378","JobAddress":"Lot 3244, Malmaison Crescent\nTRUGANINA \nVIC 3029 AUS","ConstructionRegion":null,"JobCustomer":{"CustomerAccountNumber":"004284","Name":"Mrs Sabeena Ananthan \u0026 Mr Arvind Ananthan","PostalAddress":"4/14  McCarron Parade\nESSENDON \nVIC 3040 AUS","IsActiveCustomer":true},"JobContactPeople":[{"IsPrimaryContact":true,"Name":"Sabeena Ananthan","ContactPersonPhotoURL":null,"ContactPersonDetails":{"Email":"sabeena.mohd@ymail.com","Phone":null,"Mobile":"0413682967"}},{"IsPrimaryContact":false,"Name":"Arvind Ananthan","ContactPersonPhotoURL":null,"ContactPersonDetails":{"Email":null,"Phone":"0415043042","Mobile":null}}],"SelectedHouseType":"Flemming VK1","SelectedFacade":"Eden","CurrentPhase":"Pre-Administration","CurrentSubPhase":"Prospect","CurrentPhaseID":null,"CurrentSubPhaseID":null,"CurrentPhasePercentageComplete":"0.0000000000000000","TotalPercentageComplete":"0.0000000000000000","OpportunityID":"VHE-017910","JobTeamMembers":[{"JobNumber":"304378","Responsibility":"Sales Consultant","EmployeeName":"Eris Clements","EmployeePhotoURL":"EClements","EmployeeContactDetails":{"Email":"EClements@henley.com.au","Phone":"+61383066034","Mobile":null}}],"Company":"vhe","DisplayEmployeePhotos":false,"JobStatus":"Active","ProspectType":"Certainty Marketing","WebActive":"0","Brand":"Henley"}]}